japy/__init__.py
japy/__main__.py
japy/core.py
japy/japy.png
japy/japy.py
japy/ジャパイ.japy
japy/ジャパイ.py
japy_lang-0.2.0.dist-info/METADATA
japy_lang-0.2.0.dist-info/WHEEL
japy_lang-0.2.0.dist-info/entry_points.txt
japy_lang-0.2.0.dist-info/licenses/LICENSE
japy_lang-0.2.0.dist-info/RECORD
