Metadata-Version: 2.4
Name: japy-lang
Version: 0.2.0
Summary: JaPy is a Python dialect in Japanese.
Project-URL: Homepage, https://github.com/satoi8080/JaPy
Project-URL: Repository, https://github.com/satoi8080/JaPy
Project-URL: Issues, https://github.com/satoi8080/JaPy/issues
Author-email: Zhe <i@zzhe.dev>
License: MIT
License-File: LICENSE
Keywords: japanese,katakana,programming-language,python,transpiler
Classifier: Development Status :: 3 - Alpha
Classifier: Intended Audience :: Developers
Classifier: License :: OSI Approved :: MIT License
Classifier: Natural Language :: Japanese
Classifier: Programming Language :: Python :: 3
Classifier: Programming Language :: Python :: 3.12
Classifier: Topic :: Software Development :: Compilers
Classifier: Topic :: Software Development :: Interpreters
Requires-Python: >=3.12
Requires-Dist: absl-py>=2.3.0
Requires-Dist: pre-commit>=4.2.0
